reddit_stock_sentiment/__init__.py
reddit_stock_sentiment/reddit_stock_sentiment.py
reddit_stock_sentiment-0.1.3.dist-info/AUTHORS.rst
reddit_stock_sentiment-0.1.3.dist-info/LICENSE
reddit_stock_sentiment-0.1.3.dist-info/METADATA
reddit_stock_sentiment-0.1.3.dist-info/WHEEL
reddit_stock_sentiment-0.1.3.dist-info/top_level.txt
reddit_stock_sentiment-0.1.3.dist-info/RECORD
