Metadata-Version: 2.1
Name: reddit-stock-sentiment
Version: 0.1.3
Summary: Simple class using spacy and nltk to identitify stocks and sentiment on Reddit forums
Home-page: https://github.com/paul-armstrong-dev/reddit_stock_sentiment
Author: Paul Armstrong
Author-email: paul.armstrong211@gmail.com
License: MIT license
Keywords: reddit_stock_sentiment
Platform: UNKNOWN
Classifier: Development Status :: 2 - Pre-Alpha
Classifier: Intended Audience :: Developers
Classifier: License :: OSI Approved :: MIT License
Classifier: Natural Language :: English
Classifier: Programming Language :: Python :: 3
Classifier: Programming Language :: Python :: 3.6
Classifier: Programming Language :: Python :: 3.7
Classifier: Programming Language :: Python :: 3.8
Requires-Python: >=3.6
License-File: LICENSE
License-File: AUTHORS.rst
Requires-Dist: pandas (==1.3.1)
Requires-Dist: spacy (==3.1.1)
Requires-Dist: nltk (==3.6.2)
Requires-Dist: loguru (==0.5.3)
Requires-Dist: python-dotenv (==0.19.0)
Requires-Dist: praw (==7.4.0)
